{
    "num": 1,
    "last_modified": 1424309210305,
    "geofences": [
        {
            "id": 5,
            "data": {
                "android":{"message": "More Park"}
            },
            "trigger_type": "enter",
            "expiry_time": 2056720182000,
            "locations": [
                {
                    "id": 88,
                    "name": "Kensington Market",
                    "lat": 43.654834,
                    "long": -79.4028751,
                    "rad": 400
                }
            ]
        }
    ]
}
